{
  "emotion": "قلق",
  "aliases": [
    "anxiety",
    "توتر",
    "هم",
    "خوف من المستقبل",
    "عصبية",
    "stress",
    "worry",
    "nervous",
    "overthinking",
    "anxious",
    "stressed out",
    "متوتر",
    "مهموم",
    "شايل هم",
    "تفكير زائد"
  ],
  "description": "القلق هو استجابة طبيعية للتوتر أو الخطر المتوقع، وهو شعور بالخوف أو عدم الارتياح تجاه المستقبل. بينما هو مفيد كإشارة تحذيرية، يصبح مشكلة عندما يكون مفرطًا ومستمرًا ويؤثر على الحياة اليومية.",
  "intensity_levels": {
    "خفيف": {
      "description": "شعور بسيط بالتوتر أو عدم الارتياح قبل حدث معين، وعادة ما يكون محفزًا.",
      "typical_triggers": [
        "امتحان قادم",
        "مقابلة عمل",
        "محادثة مهمة",
        "تأخير عن موعد",
        "انتظار نتيجة"
      ]
    },
    "متوسط": {
      "description": "شعور مستمر بالهم والتفكير الزائد الذي يؤثر على التركيز ويسبب أعراضًا جسدية خفيفة.",
      "typical_triggers": [
        "مشاكل مالية",
        "ضغط عمل مستمر",
        "مشاكل في العلاقات",
        "مخاوف صحية",
        "عدم اليقين بشأن المستقبل"
      ]
    },
    "عميق": {
      "description": "قلق شديد يمكن أن يؤدي إلى نوبات هلع، تجنب المواقف الاجتماعية، والشعور بفقدان السيطرة بشكل دائم.",
      "typical_triggers": [
        "أزمة كبيرة (شخصية أو مهنية)",
        "تغييرات حياتية جذرية",
        "صدمات سابقة",
        "قلق اجتماعي شديد",
        "مخاوف وجودية"
      ]
    }
  },
  "related_concepts": {
    "الخوف": [
      "رهبة",
      "فزع",
      "الخوف من المجهول",
      "تجنب"
    ],
    "الشك": [
      "عدم اليقين",
      "تردد",
      "صعوبة اتخاذ القرار",
      "التشكيك في النفس"
    ],
    "الكمالية": [
      "الخوف من ارتكاب الأخطاء",
      "معايير عالية غير واقعية",
      "نقد ذاتي حاد",
      "تسويف"
    ],
    "فقدان السيطرة": [
      "الشعور بأن الأمور خارجة عن السيطرة",
      "الحاجة المفرطة للتخطيط",
      "عدم تحمل الغموض"
    ],
    "الاجترار الفكري": [
      "التفكير الدائري في نفس المشكلة",
      "تحليل مفرط للمواقف",
      "سيناريوهات كارثية مستقبلية"
    ]
  },
  "physical_signs": [
    "تسارع ضربات القلب",
    "صعوبة في التنفس أو التنفس السريع",
    "تعرق أو رعشة في الأطراف",
    "صداع أو دوخة",
    "اضطرابات في المعدة أو غثيان",
    "توتر وألم في العضلات (خاصة الرقبة والكتفين)",
    "أرق وصعوبة في النوم"
  ],
  "cognitive_signs": [
    "تفكير كارثي (توقع الأسوأ دائمًا)",
    "صعوبة في التركيز والشعور بتشتت الانتباه",
    "الشعور المستمر بوجود خطر وشيك",
    "الذاكرة العاملة ضعيفة (نسيان الأشياء البسيطة)",
    "أفكار متسارعة لا يمكن إيقافها",
    "الحساسية المفرطة للنقد"
  ],
  "behavioral_signs": [
    "تجنب المواقف أو الأماكن التي تثير القلق",
    "التململ وعدم القدرة على الجلوس بهدوء",
    "التحدث بسرعة",
    "السعي المستمر للحصول على الطمأنينة من الآخرين",
    "المماطلة والتسويف بسبب الخوف من الفشل",
    "القيام بسلوكيات قهرية (مثل تفقد الأشياء مرارًا)"
  ],
  "coping_mechanisms": {
    "short_term": [
      "تمارين التنفس العميق (مثل تمرين 4-7-8)",
      "تقنية التأريض (Grounding - تسمية 5 أشياء تراها، 4 تلمسها...)",
      "المشي أو ممارسة نشاط بدني بسيط لتفريغ الطاقة",
      "تحويل التركيز إلى مهمة بسيطة (مثل ترتيب شيء ما)",
      "الحديث عن المخاوف مع شخص تثق به",
      "كتابة الأفكار المقلقة على ورقة لإخراجها من رأسك"
    ],
    "long_term": [
      "ممارسة تقنيات الاسترخاء بانتظام (التأمل، اليوغا)",
      "تحدي الأفكار القلقة وإعادة صياغتها (العلاج السلوكي المعرفي)",
      "العلاج بالتعرض التدريجي للمواقف المثيرة للقلق",
      "الحفاظ على نمط حياة صحي (نوم كافٍ، تغذية جيدة، رياضة)",
      "تقليل استهلاك الكافيين والمنبهات",
      "تعلم مهارات حل المشكلات وإدارة الوقت",
      "استشارة أخصائي نفسي"
    ]
  },
  "cultural_notes": [
    "في بعض الثقافات، قد يُنظر إلى القلق على أنه 'قلة إيمان' أو ضعف، مما يجعل الناس يترددون في طلب المساعدة.",
    "ضغوط العمل الحديثة وثقافة 'الإنجاز المستمر' تساهم بشكل كبير في زيادة مستويات القلق."
  ],
  "examples_in_sentences": [
    "أشعر بقلق شديد كلما فكرت في المستقبل.",
    "التوتر يجعل ضربات قلبي تتسارع ولا أستطيع التنفس جيدًا.",
    "أنا دائمًا شايل هم أشياء لم تحدث بعد.",
    "لا أستطيع التوقف عن التفكير الزائد في كل تفصيلة صغيرة.",
    "هذا القلق يمنعني من تجربة أي شيء جديد في حياتي."
  ],
  "mixed_languages": {
    "english_terms": [
      "anxiety",
      "stress",
      "worry",
      "nervousness",
      "panic",
      "overthinking"
    ],
    "arabic_terms": [
      "قلق",
      "توتر",
      "هم",
      "عصبية",
      "خوف"
    ]
  },
  "connections_to_emotions": {
    "related_emotions": [
      "خوف",
      "حزن",
      "إرهاق",
      "غضب",
      "إحباط"
    ],
    "opposite_emotions": [
      "سكينة",
      "هدوء",
      "طمأنينة",
      "استرخاء",
      "ثقة"
    ]
  }
}
